{
  "commodity": {
    "desc": "SOYBEANS",
    "slug": "soybeans"
  },
  "county": {
    "code": "117",
    "name": "TIOGA"
  },
  "rank": {
    "1985": {
      "count_in_nation": 1853,
      "count_in_state": 51,
      "percentile_in_nation": 0.5119,
      "percentile_in_state": 0.32,
      "rank_in_nation": 905,
      "rank_in_state": 35
    },
    "1986": {
      "count_in_nation": 1814,
      "count_in_state": 51,
      "percentile_in_nation": 0.5753,
      "percentile_in_state": 0.3,
      "rank_in_nation": 771,
      "rank_in_state": 36
    },
    "1987": {
      "count_in_nation": 1778,
      "count_in_state": 52,
      "percentile_in_nation": 0.4941,
      "percentile_in_state": 0.0784,
      "rank_in_nation": 900,
      "rank_in_state": 48
    },
    "1988": {
      "count_in_nation": 1814,
      "count_in_state": 52,
      "percentile_in_nation": 0.8715,
      "percentile_in_state": 0.7255,
      "rank_in_nation": 234,
      "rank_in_state": 15
    },
    "1989": {
      "count_in_nation": 1825,
      "count_in_state": 52,
      "percentile_in_nation": 0.5965,
      "percentile_in_state": 0.4314,
      "rank_in_nation": 737,
      "rank_in_state": 30
    },
    "1990": {
      "count_in_nation": 1773,
      "count_in_state": 52,
      "percentile_in_nation": 0.64,
      "percentile_in_state": 0.3137,
      "rank_in_nation": 639,
      "rank_in_state": 36
    },
    "1991": {
      "count_in_nation": 1740,
      "count_in_state": 51,
      "percentile_in_nation": 0.161,
      "percentile_in_state": 0.08,
      "rank_in_nation": 1460,
      "rank_in_state": 47
    },
    "1992": {
      "count_in_nation": 1739,
      "count_in_state": 51,
      "percentile_in_nation": 0.5794,
      "percentile_in_state": 0.38,
      "rank_in_nation": 732,
      "rank_in_state": 32
    },
    "1993": {
      "count_in_nation": 1677,
      "count_in_state": 51,
      "percentile_in_nation": 0.5495,
      "percentile_in_state": 0.12,
      "rank_in_nation": 756,
      "rank_in_state": 45
    },
    "1994": {
      "count_in_nation": 1660,
      "count_in_state": 51,
      "percentile_in_nation": 0.6154,
      "percentile_in_state": 0.52,
      "rank_in_nation": 639,
      "rank_in_state": 25
    },
    "1998": {
      "count_in_nation": 1683,
      "count_in_state": 45,
      "percentile_in_nation": 0.3841,
      "percentile_in_state": 0.0,
      "rank_in_nation": 1037,
      "rank_in_state": 45
    },
    "1999": {
      "count_in_nation": 1633,
      "count_in_state": 46,
      "percentile_in_nation": 0.6183,
      "percentile_in_state": 0.8444,
      "rank_in_nation": 624,
      "rank_in_state": 8
    },
    "2000": {
      "count_in_nation": 1663,
      "count_in_state": 45,
      "percentile_in_nation": 0.4055,
      "percentile_in_state": 0.0,
      "rank_in_nation": 989,
      "rank_in_state": 45
    },
    "2001": {
      "count_in_nation": 1648,
      "count_in_state": 45,
      "percentile_in_nation": 0.3825,
      "percentile_in_state": 0.4318,
      "rank_in_nation": 1018,
      "rank_in_state": 26
    },
    "2002": {
      "count_in_nation": 1631,
      "count_in_state": 52,
      "percentile_in_nation": 0.2687,
      "percentile_in_state": 0.4706,
      "rank_in_nation": 1193,
      "rank_in_state": 28
    },
    "2003": {
      "count_in_nation": 1625,
      "count_in_state": 52,
      "percentile_in_nation": 0.7303,
      "percentile_in_state": 0.2549,
      "rank_in_nation": 439,
      "rank_in_state": 39
    },
    "2005": {
      "count_in_nation": 1650,
      "count_in_state": 53,
      "percentile_in_nation": 0.7307,
      "percentile_in_state": 0.9231,
      "rank_in_nation": 445,
      "rank_in_state": 5
    },
    "2012": {
      "count_in_nation": 1483,
      "count_in_state": 51,
      "percentile_in_nation": 0.4966,
      "percentile_in_state": 0.12,
      "rank_in_nation": 747,
      "rank_in_state": 45
    },
    "2013": {
      "count_in_nation": 1395,
      "count_in_state": 50,
      "percentile_in_nation": 0.6198,
      "percentile_in_state": 0.4694,
      "rank_in_nation": 531,
      "rank_in_state": 27
    },
    "2014": {
      "count_in_nation": 1458,
      "count_in_state": 44,
      "percentile_in_nation": 0.2032,
      "percentile_in_state": 0.0698,
      "rank_in_nation": 1162,
      "rank_in_state": 41
    },
    "2017": {
      "count_in_nation": 1381,
      "count_in_state": 46,
      "percentile_in_nation": 0.1739,
      "percentile_in_state": 0.2889,
      "rank_in_nation": 1141,
      "rank_in_state": 33
    },
    "2020": {
      "count_in_nation": 1499,
      "count_in_state": 46,
      "percentile_in_nation": 0.2096,
      "percentile_in_state": 0.3111,
      "rank_in_nation": 1185,
      "rank_in_state": 32
    },
    "2021": {
      "count_in_nation": 1352,
      "count_in_state": 50,
      "percentile_in_nation": 0.2213,
      "percentile_in_state": 0.0,
      "rank_in_nation": 1053,
      "rank_in_state": 50
    },
    "2022": {
      "count_in_nation": 1396,
      "count_in_state": 48,
      "percentile_in_nation": 0.1527,
      "percentile_in_state": 0.234,
      "rank_in_nation": 1183,
      "rank_in_state": 37
    },
    "2023": {
      "count_in_nation": 1306,
      "count_in_state": 47,
      "percentile_in_nation": 0.2782,
      "percentile_in_state": 0.2174,
      "rank_in_nation": 943,
      "rank_in_state": 37
    }
  },
  "revenue": {
    "1985": {
      "marketing_year": "1985",
      "price": 4.75,
      "revenue_per_harvested_acre": 142.5,
      "revenue_per_planted_acre": 142.5,
      "yield": 30.0
    },
    "1986": {
      "marketing_year": "1986",
      "price": 4.85,
      "revenue_per_harvested_acre": 150.35,
      "revenue_per_planted_acre": 150.35,
      "yield": 31.0
    },
    "1987": {
      "marketing_year": "1987",
      "price": 6.2,
      "revenue_per_harvested_acre": 179.8,
      "revenue_per_planted_acre": 179.8,
      "yield": 29.0
    },
    "1988": {
      "marketing_year": "1988",
      "price": 7.45,
      "revenue_per_harvested_acre": 238.4,
      "revenue_per_planted_acre": 238.4,
      "yield": 32.0
    },
    "1989": {
      "marketing_year": "1989",
      "price": 5.65,
      "revenue_per_harvested_acre": 175.15,
      "revenue_per_planted_acre": 155.6889,
      "yield": 31.0
    },
    "1990": {
      "marketing_year": "1990",
      "price": 5.7,
      "revenue_per_harvested_acre": 193.8,
      "revenue_per_planted_acre": 172.2667,
      "yield": 34.0
    },
    "1991": {
      "marketing_year": "1991",
      "price": 5.53,
      "revenue_per_harvested_acre": 127.19,
      "revenue_per_planted_acre": 127.19,
      "yield": 23.0
    },
    "1992": {
      "marketing_year": "1992",
      "price": 5.47,
      "revenue_per_harvested_acre": 191.45,
      "revenue_per_planted_acre": 191.45,
      "yield": 35.0
    },
    "1993": {
      "marketing_year": "1993",
      "price": 6.33,
      "revenue_per_harvested_acre": 196.23,
      "revenue_per_planted_acre": 196.23,
      "yield": 31.0
    },
    "1994": {
      "marketing_year": "1994",
      "price": 5.38,
      "revenue_per_harvested_acre": 209.82,
      "revenue_per_planted_acre": 209.82,
      "yield": 39.0
    },
    "1998": {
      "marketing_year": "1998",
      "price": 4.95,
      "revenue_per_harvested_acre": 138.6,
      "revenue_per_planted_acre": 115.5,
      "yield": 28.0
    },
    "1999": {
      "marketing_year": "1999",
      "price": 4.6,
      "revenue_per_harvested_acre": 161.0,
      "revenue_per_planted_acre": 161.0,
      "yield": 35.0
    },
    "2000": {
      "marketing_year": "2000",
      "price": 4.37,
      "revenue_per_harvested_acre": 139.84,
      "revenue_per_planted_acre": 119.8629,
      "yield": 32.0
    },
    "2001": {
      "marketing_year": "2001",
      "price": 4.26,
      "revenue_per_harvested_acre": 140.58,
      "revenue_per_planted_acre": 120.4971,
      "yield": 33.0
    },
    "2002": {
      "marketing_year": "2002",
      "price": 5.9,
      "revenue_per_harvested_acre": 147.5,
      "revenue_per_planted_acre": 147.5,
      "yield": 25.0
    },
    "2003": {
      "marketing_year": "2003",
      "price": 7.33,
      "revenue_per_harvested_acre": 280.739,
      "revenue_per_planted_acre": 280.9833,
      "yield": 38.3
    },
    "2005": {
      "marketing_year": "2005",
      "price": 5.6,
      "revenue_per_harvested_acre": 252.0,
      "revenue_per_planted_acre": 210.0,
      "yield": 45.0
    },
    "2012": {
      "marketing_year": "2012",
      "price": 14.2,
      "revenue_per_harvested_acre": 573.68,
      "revenue_per_planted_acre": 528.5556,
      "yield": 40.4
    },
    "2013": {
      "marketing_year": "2013",
      "price": 13.0,
      "revenue_per_harvested_acre": 603.2,
      "revenue_per_planted_acre": 603.4167,
      "yield": 46.4
    },
    "2014": {
      "marketing_year": "2014",
      "price": 9.8,
      "revenue_per_harvested_acre": 360.64,
      "revenue_per_planted_acre": 343.0,
      "yield": 36.8
    },
    "2017": {
      "marketing_year": "2017",
      "price": 9.34,
      "revenue_per_harvested_acre": 356.788,
      "revenue_per_planted_acre": 348.6933,
      "yield": 38.2
    },
    "2020": {
      "marketing_year": "2020",
      "price": 11.3,
      "revenue_per_harvested_acre": 452.0,
      "revenue_per_planted_acre": 422.7529,
      "yield": 40.0
    },
    "2021": {
      "marketing_year": "2021",
      "price": 13.8,
      "revenue_per_harvested_acre": 556.14,
      "revenue_per_planted_acre": 505.5818,
      "yield": 40.3
    },
    "2022": {
      "marketing_year": "2022",
      "price": 14.5,
      "revenue_per_harvested_acre": 494.45,
      "revenue_per_planted_acre": 485.3235,
      "yield": 34.1
    },
    "2023": {
      "marketing_year": "2023",
      "price": 12.5,
      "revenue_per_harvested_acre": 513.75,
      "revenue_per_planted_acre": 505.7292,
      "yield": 41.1
    }
  },
  "schema_version": 3,
  "state": {
    "alpha": "PA",
    "fips": "42",
    "name": "PENNSYLVANIA"
  },
  "yield_trend": {
    "slope_bu_per_year": 0.2892,
    "trailing_10yr_avg": {
      "1989": 30.6,
      "1990": 31.17,
      "1991": 30.0,
      "1992": 30.62,
      "1993": 30.67,
      "1994": 31.5,
      "1998": 31.57,
      "1999": 32.14,
      "2000": 31.86,
      "2001": 33.29,
      "2002": 31.86,
      "2003": 32.9,
      "2005": 33.76,
      "2020": 40.36,
      "2021": 40.35,
      "2022": 39.3,
      "2023": 38.42
    },
    "trailing_5yr_avg": {
      "1987": 30.0,
      "1988": 30.5,
      "1989": 30.6,
      "1990": 31.4,
      "1991": 29.8,
      "1992": 31.0,
      "1993": 30.8,
      "1994": 32.4,
      "2000": 31.67,
      "2001": 32.0,
      "2002": 30.6,
      "2003": 32.66,
      "2005": 35.33,
      "2014": 41.2,
      "2017": 40.47,
      "2021": 39.5,
      "2022": 38.13,
      "2023": 38.88
    },
    "yoy_pct": {
      "1986": 3.33,
      "1987": -6.45,
      "1988": 10.34,
      "1989": -3.12,
      "1990": 9.68,
      "1991": -32.35,
      "1992": 52.17,
      "1993": -11.43,
      "1994": 25.81,
      "1999": 25.0,
      "2000": -8.57,
      "2001": 3.12,
      "2002": -24.24,
      "2003": 53.2,
      "2013": 14.85,
      "2014": -20.69,
      "2021": 0.75,
      "2022": -15.38,
      "2023": 20.53
    }
  }
}
