{
  "commodity": {
    "desc": "SOYBEANS",
    "slug": "soybeans"
  },
  "county": {
    "code": "147",
    "name": "SPENCER"
  },
  "rank": {
    "1937": {
      "count_in_nation": 293,
      "count_in_state": 92,
      "percentile_in_nation": 0.2979,
      "percentile_in_state": 0.2088,
      "rank_in_nation": 206,
      "rank_in_state": 73
    },
    "1938": {
      "count_in_nation": 336,
      "count_in_state": 92,
      "percentile_in_nation": 0.3791,
      "percentile_in_state": 0.3846,
      "rank_in_nation": 209,
      "rank_in_state": 57
    },
    "1939": {
      "count_in_nation": 361,
      "count_in_state": 92,
      "percentile_in_nation": 0.1833,
      "percentile_in_state": 0.0879,
      "rank_in_nation": 295,
      "rank_in_state": 84
    },
    "1940": {
      "count_in_nation": 506,
      "count_in_state": 92,
      "percentile_in_nation": 0.1921,
      "percentile_in_state": 0.3187,
      "rank_in_nation": 409,
      "rank_in_state": 63
    },
    "1941": {
      "count_in_nation": 579,
      "count_in_state": 92,
      "percentile_in_nation": 0.4931,
      "percentile_in_state": 0.3297,
      "rank_in_nation": 294,
      "rank_in_state": 62
    },
    "1942": {
      "count_in_nation": 653,
      "count_in_state": 92,
      "percentile_in_nation": 0.3298,
      "percentile_in_state": 0.0549,
      "rank_in_nation": 438,
      "rank_in_state": 87
    },
    "1943": {
      "count_in_nation": 731,
      "count_in_state": 92,
      "percentile_in_nation": 0.2836,
      "percentile_in_state": 0.011,
      "rank_in_nation": 524,
      "rank_in_state": 91
    },
    "1944": {
      "count_in_nation": 836,
      "count_in_state": 92,
      "percentile_in_nation": 0.4108,
      "percentile_in_state": 0.1868,
      "rank_in_nation": 493,
      "rank_in_state": 75
    },
    "1945": {
      "count_in_nation": 738,
      "count_in_state": 92,
      "percentile_in_nation": 0.5875,
      "percentile_in_state": 0.2088,
      "rank_in_nation": 305,
      "rank_in_state": 73
    },
    "1946": {
      "count_in_nation": 739,
      "count_in_state": 92,
      "percentile_in_nation": 0.378,
      "percentile_in_state": 0.1538,
      "rank_in_nation": 460,
      "rank_in_state": 78
    },
    "1947": {
      "count_in_nation": 882,
      "count_in_state": 92,
      "percentile_in_nation": 0.4711,
      "percentile_in_state": 0.0549,
      "rank_in_nation": 467,
      "rank_in_state": 87
    },
    "1948": {
      "count_in_nation": 904,
      "count_in_state": 92,
      "percentile_in_nation": 0.392,
      "percentile_in_state": 0.1099,
      "rank_in_nation": 550,
      "rank_in_state": 82
    },
    "1949": {
      "count_in_nation": 980,
      "count_in_state": 92,
      "percentile_in_nation": 0.2686,
      "percentile_in_state": 0.022,
      "rank_in_nation": 717,
      "rank_in_state": 90
    },
    "1950": {
      "count_in_nation": 994,
      "count_in_state": 92,
      "percentile_in_nation": 0.3414,
      "percentile_in_state": 0.0989,
      "rank_in_nation": 655,
      "rank_in_state": 83
    },
    "1951": {
      "count_in_nation": 1009,
      "count_in_state": 92,
      "percentile_in_nation": 0.4692,
      "percentile_in_state": 0.1978,
      "rank_in_nation": 536,
      "rank_in_state": 74
    },
    "1952": {
      "count_in_nation": 1025,
      "count_in_state": 92,
      "percentile_in_nation": 0.2041,
      "percentile_in_state": 0.0549,
      "rank_in_nation": 816,
      "rank_in_state": 87
    },
    "1953": {
      "count_in_nation": 1002,
      "count_in_state": 92,
      "percentile_in_nation": 0.2368,
      "percentile_in_state": 0.022,
      "rank_in_nation": 765,
      "rank_in_state": 90
    },
    "1954": {
      "count_in_nation": 1068,
      "count_in_state": 92,
      "percentile_in_nation": 0.4695,
      "percentile_in_state": 0.0549,
      "rank_in_nation": 567,
      "rank_in_state": 87
    },
    "1955": {
      "count_in_nation": 1078,
      "count_in_state": 92,
      "percentile_in_nation": 0.2683,
      "percentile_in_state": 0.0879,
      "rank_in_nation": 789,
      "rank_in_state": 84
    },
    "1956": {
      "count_in_nation": 1064,
      "count_in_state": 92,
      "percentile_in_nation": 0.8523,
      "percentile_in_state": 0.6374,
      "rank_in_nation": 158,
      "rank_in_state": 34
    },
    "1957": {
      "count_in_nation": 1036,
      "count_in_state": 92,
      "percentile_in_nation": 0.3092,
      "percentile_in_state": 0.0549,
      "rank_in_nation": 716,
      "rank_in_state": 87
    },
    "1958": {
      "count_in_nation": 1052,
      "count_in_state": 92,
      "percentile_in_nation": 0.5576,
      "percentile_in_state": 0.1319,
      "rank_in_nation": 466,
      "rank_in_state": 80
    },
    "1959": {
      "count_in_nation": 1131,
      "count_in_state": 92,
      "percentile_in_nation": 0.6566,
      "percentile_in_state": 0.3077,
      "rank_in_nation": 389,
      "rank_in_state": 64
    },
    "1960": {
      "count_in_nation": 1167,
      "count_in_state": 92,
      "percentile_in_nation": 0.1913,
      "percentile_in_state": 0.0,
      "rank_in_nation": 944,
      "rank_in_state": 92
    },
    "1961": {
      "count_in_nation": 1238,
      "count_in_state": 92,
      "percentile_in_nation": 0.5732,
      "percentile_in_state": 0.1099,
      "rank_in_nation": 529,
      "rank_in_state": 82
    },
    "1962": {
      "count_in_nation": 1253,
      "count_in_state": 92,
      "percentile_in_nation": 0.2077,
      "percentile_in_state": 0.011,
      "rank_in_nation": 993,
      "rank_in_state": 91
    },
    "1963": {
      "count_in_nation": 1253,
      "count_in_state": 92,
      "percentile_in_nation": 0.5958,
      "percentile_in_state": 0.0989,
      "rank_in_nation": 507,
      "rank_in_state": 83
    },
    "1964": {
      "count_in_nation": 1288,
      "count_in_state": 92,
      "percentile_in_nation": 0.6752,
      "percentile_in_state": 0.3187,
      "rank_in_nation": 419,
      "rank_in_state": 63
    },
    "1965": {
      "count_in_nation": 1310,
      "count_in_state": 92,
      "percentile_in_nation": 0.7479,
      "percentile_in_state": 0.2527,
      "rank_in_nation": 331,
      "rank_in_state": 69
    },
    "1966": {
      "count_in_nation": 1339,
      "count_in_state": 92,
      "percentile_in_nation": 0.5815,
      "percentile_in_state": 0.2527,
      "rank_in_nation": 561,
      "rank_in_state": 69
    },
    "1967": {
      "count_in_nation": 1399,
      "count_in_state": 92,
      "percentile_in_nation": 0.9156,
      "percentile_in_state": 0.9011,
      "rank_in_nation": 119,
      "rank_in_state": 10
    },
    "1968": {
      "count_in_nation": 1453,
      "count_in_state": 92,
      "percentile_in_nation": 0.8258,
      "percentile_in_state": 0.4725,
      "rank_in_nation": 254,
      "rank_in_state": 49
    },
    "1969": {
      "count_in_nation": 1471,
      "count_in_state": 92,
      "percentile_in_nation": 0.7878,
      "percentile_in_state": 0.3407,
      "rank_in_nation": 313,
      "rank_in_state": 61
    },
    "1970": {
      "count_in_nation": 1460,
      "count_in_state": 92,
      "percentile_in_nation": 0.6875,
      "percentile_in_state": 0.0989,
      "rank_in_nation": 457,
      "rank_in_state": 83
    },
    "1971": {
      "count_in_nation": 1456,
      "count_in_state": 92,
      "percentile_in_nation": 0.7684,
      "percentile_in_state": 0.3297,
      "rank_in_nation": 338,
      "rank_in_state": 62
    },
    "1972": {
      "count_in_nation": 1724,
      "count_in_state": 92,
      "percentile_in_nation": 0.6036,
      "percentile_in_state": 0.2418,
      "rank_in_nation": 684,
      "rank_in_state": 70
    },
    "1973": {
      "count_in_nation": 1761,
      "count_in_state": 92,
      "percentile_in_nation": 0.5528,
      "percentile_in_state": 0.1648,
      "rank_in_nation": 788,
      "rank_in_state": 77
    },
    "1974": {
      "count_in_nation": 1817,
      "count_in_state": 92,
      "percentile_in_nation": 0.6894,
      "percentile_in_state": 0.5714,
      "rank_in_nation": 565,
      "rank_in_state": 40
    },
    "1975": {
      "count_in_nation": 1792,
      "count_in_state": 92,
      "percentile_in_nation": 0.7527,
      "percentile_in_state": 0.2967,
      "rank_in_nation": 444,
      "rank_in_state": 65
    },
    "1976": {
      "count_in_nation": 1790,
      "count_in_state": 92,
      "percentile_in_nation": 0.8099,
      "percentile_in_state": 0.1978,
      "rank_in_nation": 341,
      "rank_in_state": 74
    },
    "1977": {
      "count_in_nation": 1839,
      "count_in_state": 92,
      "percentile_in_nation": 0.7242,
      "percentile_in_state": 0.2418,
      "rank_in_nation": 508,
      "rank_in_state": 70
    },
    "1978": {
      "count_in_nation": 1857,
      "count_in_state": 92,
      "percentile_in_nation": 0.6724,
      "percentile_in_state": 0.2527,
      "rank_in_nation": 609,
      "rank_in_state": 69
    },
    "1979": {
      "count_in_nation": 1882,
      "count_in_state": 92,
      "percentile_in_nation": 0.6528,
      "percentile_in_state": 0.2857,
      "rank_in_nation": 654,
      "rank_in_state": 66
    },
    "1980": {
      "count_in_nation": 1866,
      "count_in_state": 92,
      "percentile_in_nation": 0.7056,
      "percentile_in_state": 0.1538,
      "rank_in_nation": 550,
      "rank_in_state": 78
    },
    "1981": {
      "count_in_nation": 1835,
      "count_in_state": 92,
      "percentile_in_nation": 0.747,
      "percentile_in_state": 0.5495,
      "rank_in_nation": 465,
      "rank_in_state": 42
    },
    "1982": {
      "count_in_nation": 1813,
      "count_in_state": 92,
      "percentile_in_nation": 0.6992,
      "percentile_in_state": 0.2088,
      "rank_in_nation": 546,
      "rank_in_state": 73
    },
    "1983": {
      "count_in_nation": 1870,
      "count_in_state": 92,
      "percentile_in_nation": 0.344,
      "percentile_in_state": 0.044,
      "rank_in_nation": 1227,
      "rank_in_state": 88
    },
    "1984": {
      "count_in_nation": 1875,
      "count_in_state": 92,
      "percentile_in_nation": 0.7028,
      "percentile_in_state": 0.2747,
      "rank_in_nation": 558,
      "rank_in_state": 67
    },
    "1985": {
      "count_in_nation": 1853,
      "count_in_state": 92,
      "percentile_in_nation": 0.6571,
      "percentile_in_state": 0.0879,
      "rank_in_nation": 636,
      "rank_in_state": 84
    },
    "1986": {
      "count_in_nation": 1814,
      "count_in_state": 92,
      "percentile_in_nation": 0.7038,
      "percentile_in_state": 0.3407,
      "rank_in_nation": 538,
      "rank_in_state": 61
    },
    "1987": {
      "count_in_nation": 1778,
      "count_in_state": 92,
      "percentile_in_nation": 0.4986,
      "percentile_in_state": 0.0659,
      "rank_in_nation": 892,
      "rank_in_state": 86
    },
    "1988": {
      "count_in_nation": 1814,
      "count_in_state": 92,
      "percentile_in_nation": 0.5825,
      "percentile_in_state": 0.4615,
      "rank_in_nation": 758,
      "rank_in_state": 50
    },
    "1989": {
      "count_in_nation": 1825,
      "count_in_state": 92,
      "percentile_in_nation": 0.6913,
      "percentile_in_state": 0.1538,
      "rank_in_nation": 564,
      "rank_in_state": 78
    },
    "1990": {
      "count_in_nation": 1773,
      "count_in_state": 92,
      "percentile_in_nation": 0.6117,
      "percentile_in_state": 0.0989,
      "rank_in_nation": 689,
      "rank_in_state": 83
    },
    "1991": {
      "count_in_nation": 1740,
      "count_in_state": 92,
      "percentile_in_nation": 0.4359,
      "percentile_in_state": 0.0659,
      "rank_in_nation": 982,
      "rank_in_state": 86
    },
    "1992": {
      "count_in_nation": 1739,
      "count_in_state": 92,
      "percentile_in_nation": 0.767,
      "percentile_in_state": 0.2418,
      "rank_in_nation": 406,
      "rank_in_state": 70
    },
    "1993": {
      "count_in_nation": 1677,
      "count_in_state": 92,
      "percentile_in_nation": 0.6993,
      "percentile_in_state": 0.0,
      "rank_in_nation": 505,
      "rank_in_state": 92
    },
    "1994": {
      "count_in_nation": 1660,
      "count_in_state": 92,
      "percentile_in_nation": 0.6184,
      "percentile_in_state": 0.1209,
      "rank_in_nation": 634,
      "rank_in_state": 81
    },
    "1995": {
      "count_in_nation": 1622,
      "count_in_state": 91,
      "percentile_in_nation": 0.5848,
      "percentile_in_state": 0.0444,
      "rank_in_nation": 674,
      "rank_in_state": 87
    },
    "1996": {
      "count_in_nation": 1633,
      "count_in_state": 91,
      "percentile_in_nation": 0.6011,
      "percentile_in_state": 0.3889,
      "rank_in_nation": 652,
      "rank_in_state": 56
    },
    "1997": {
      "count_in_nation": 1683,
      "count_in_state": 92,
      "percentile_in_nation": 0.5143,
      "percentile_in_state": 0.1099,
      "rank_in_nation": 818,
      "rank_in_state": 82
    },
    "1998": {
      "count_in_nation": 1683,
      "count_in_state": 88,
      "percentile_in_nation": 0.4108,
      "percentile_in_state": 0.0,
      "rank_in_nation": 992,
      "rank_in_state": 88
    },
    "1999": {
      "count_in_nation": 1633,
      "count_in_state": 88,
      "percentile_in_nation": 0.2641,
      "percentile_in_state": 0.0115,
      "rank_in_nation": 1202,
      "rank_in_state": 87
    },
    "2000": {
      "count_in_nation": 1663,
      "count_in_state": 88,
      "percentile_in_nation": 0.8249,
      "percentile_in_state": 0.3448,
      "rank_in_nation": 292,
      "rank_in_state": 58
    },
    "2001": {
      "count_in_nation": 1648,
      "count_in_state": 88,
      "percentile_in_nation": 0.7887,
      "percentile_in_state": 0.1149,
      "rank_in_nation": 349,
      "rank_in_state": 78
    },
    "2002": {
      "count_in_nation": 1631,
      "count_in_state": 88,
      "percentile_in_nation": 0.4092,
      "percentile_in_state": 0.092,
      "rank_in_nation": 964,
      "rank_in_state": 80
    },
    "2003": {
      "count_in_nation": 1625,
      "count_in_state": 88,
      "percentile_in_nation": 0.9064,
      "percentile_in_state": 0.954,
      "rank_in_nation": 153,
      "rank_in_state": 5
    },
    "2004": {
      "count_in_nation": 1678,
      "count_in_state": 88,
      "percentile_in_nation": 0.5128,
      "percentile_in_state": 0.0,
      "rank_in_nation": 818,
      "rank_in_state": 88
    },
    "2005": {
      "count_in_nation": 1650,
      "count_in_state": 88,
      "percentile_in_nation": 0.8005,
      "percentile_in_state": 0.3448,
      "rank_in_nation": 330,
      "rank_in_state": 58
    },
    "2006": {
      "count_in_nation": 1611,
      "count_in_state": 88,
      "percentile_in_nation": 0.659,
      "percentile_in_state": 0.1149,
      "rank_in_nation": 550,
      "rank_in_state": 78
    },
    "2007": {
      "count_in_nation": 1537,
      "count_in_state": 88,
      "percentile_in_nation": 0.5833,
      "percentile_in_state": 0.2644,
      "rank_in_nation": 641,
      "rank_in_state": 65
    },
    "2008": {
      "count_in_nation": 1335,
      "count_in_state": 91,
      "percentile_in_nation": 0.5375,
      "percentile_in_state": 0.1333,
      "rank_in_nation": 618,
      "rank_in_state": 79
    },
    "2009": {
      "count_in_nation": 1410,
      "count_in_state": 91,
      "percentile_in_nation": 0.7963,
      "percentile_in_state": 0.6,
      "rank_in_nation": 288,
      "rank_in_state": 37
    },
    "2010": {
      "count_in_nation": 1523,
      "count_in_state": 90,
      "percentile_in_nation": 0.5197,
      "percentile_in_state": 0.191,
      "rank_in_nation": 732,
      "rank_in_state": 73
    },
    "2011": {
      "count_in_nation": 1447,
      "count_in_state": 86,
      "percentile_in_nation": 0.4253,
      "percentile_in_state": 0.1529,
      "rank_in_nation": 832,
      "rank_in_state": 73
    },
    "2012": {
      "count_in_nation": 1483,
      "count_in_state": 87,
      "percentile_in_nation": 0.608,
      "percentile_in_state": 0.5465,
      "rank_in_nation": 582,
      "rank_in_state": 40
    },
    "2013": {
      "count_in_nation": 1395,
      "count_in_state": 75,
      "percentile_in_nation": 0.8422,
      "percentile_in_state": 0.5135,
      "rank_in_nation": 221,
      "rank_in_state": 37
    },
    "2014": {
      "count_in_nation": 1458,
      "count_in_state": 89,
      "percentile_in_nation": 0.7104,
      "percentile_in_state": 0.2386,
      "rank_in_nation": 423,
      "rank_in_state": 68
    },
    "2015": {
      "count_in_nation": 1335,
      "count_in_state": 88,
      "percentile_in_nation": 0.7646,
      "percentile_in_state": 0.7471,
      "rank_in_nation": 315,
      "rank_in_state": 23
    },
    "2016": {
      "count_in_nation": 1379,
      "count_in_state": 83,
      "percentile_in_nation": 0.6205,
      "percentile_in_state": 0.2073,
      "rank_in_nation": 524,
      "rank_in_state": 66
    },
    "2017": {
      "count_in_nation": 1381,
      "count_in_state": 89,
      "percentile_in_nation": 0.9065,
      "percentile_in_state": 0.875,
      "rank_in_nation": 130,
      "rank_in_state": 12
    },
    "2018": {
      "count_in_nation": 1209,
      "count_in_state": 84,
      "percentile_in_nation": 0.6002,
      "percentile_in_state": 0.1446,
      "rank_in_nation": 484,
      "rank_in_state": 72
    },
    "2019": {
      "count_in_nation": 1126,
      "count_in_state": 73,
      "percentile_in_nation": 0.7964,
      "percentile_in_state": 0.7083,
      "rank_in_nation": 230,
      "rank_in_state": 22
    },
    "2020": {
      "count_in_nation": 1499,
      "count_in_state": 89,
      "percentile_in_nation": 0.8578,
      "percentile_in_state": 0.5,
      "rank_in_nation": 214,
      "rank_in_state": 45
    },
    "2021": {
      "count_in_nation": 1352,
      "count_in_state": 74,
      "percentile_in_nation": 0.8238,
      "percentile_in_state": 0.5479,
      "rank_in_nation": 239,
      "rank_in_state": 34
    },
    "2024": {
      "count_in_nation": 1148,
      "count_in_state": 74,
      "percentile_in_nation": 0.7428,
      "percentile_in_state": 0.274,
      "rank_in_nation": 296,
      "rank_in_state": 54
    },
    "2025": {
      "count_in_nation": 1100,
      "count_in_state": 59,
      "percentile_in_nation": 0.6688,
      "percentile_in_state": 0.1897,
      "rank_in_nation": 365,
      "rank_in_state": 48
    }
  },
  "revenue": {
    "1940": {
      "marketing_year": "1940",
      "price": 0.95,
      "revenue_per_harvested_acre": 10.83,
      "yield": 11.4
    },
    "1941": {
      "marketing_year": "1941",
      "price": 1.54,
      "revenue_per_harvested_acre": 23.1,
      "yield": 15.0
    },
    "1942": {
      "marketing_year": "1942",
      "price": 1.61,
      "revenue_per_harvested_acre": 22.057,
      "yield": 13.7
    },
    "1943": {
      "marketing_year": "1943",
      "price": 1.79,
      "revenue_per_harvested_acre": 19.332,
      "yield": 10.8
    },
    "1944": {
      "marketing_year": "1944",
      "price": 2.04,
      "revenue_per_harvested_acre": 29.172,
      "yield": 14.3
    },
    "1945": {
      "marketing_year": "1945",
      "price": 2.06,
      "revenue_per_harvested_acre": 33.784,
      "yield": 16.4
    },
    "1946": {
      "marketing_year": "1946",
      "price": 2.53,
      "revenue_per_harvested_acre": 38.962,
      "yield": 15.4
    },
    "1947": {
      "marketing_year": "1947",
      "price": 3.33,
      "revenue_per_harvested_acre": 45.288,
      "yield": 13.6
    },
    "1948": {
      "marketing_year": "1948",
      "price": 2.27,
      "revenue_per_harvested_acre": 36.774,
      "yield": 16.2
    },
    "1949": {
      "marketing_year": "1949",
      "price": 2.14,
      "revenue_per_harvested_acre": 32.1,
      "yield": 15.0
    },
    "1950": {
      "marketing_year": "1950",
      "price": 2.4,
      "revenue_per_harvested_acre": 39.36,
      "yield": 16.4
    },
    "1951": {
      "marketing_year": "1951",
      "price": 2.73,
      "revenue_per_harvested_acre": 46.683,
      "yield": 17.1
    },
    "1952": {
      "marketing_year": "1952",
      "price": 2.72,
      "revenue_per_harvested_acre": 36.176,
      "yield": 13.3
    },
    "1953": {
      "marketing_year": "1953",
      "price": 2.67,
      "revenue_per_harvested_acre": 31.773,
      "yield": 11.9
    },
    "1954": {
      "marketing_year": "1954",
      "price": 2.47,
      "revenue_per_harvested_acre": 36.309,
      "yield": 14.7
    },
    "1955": {
      "marketing_year": "1955",
      "price": 2.28,
      "revenue_per_harvested_acre": 33.516,
      "yield": 14.7
    },
    "1956": {
      "marketing_year": "1956",
      "price": 2.19,
      "revenue_per_harvested_acre": 54.312,
      "yield": 24.8
    },
    "1957": {
      "marketing_year": "1957",
      "price": 2.09,
      "revenue_per_harvested_acre": 36.575,
      "yield": 17.5
    },
    "1958": {
      "marketing_year": "1958",
      "price": 1.99,
      "revenue_per_harvested_acre": 45.372,
      "yield": 22.8
    },
    "1959": {
      "marketing_year": "1959",
      "price": 1.98,
      "revenue_per_harvested_acre": 47.322,
      "yield": 23.9
    },
    "1960": {
      "marketing_year": "1960",
      "price": 2.16,
      "revenue_per_harvested_acre": 36.72,
      "yield": 17.0
    },
    "1961": {
      "marketing_year": "1961",
      "price": 2.25,
      "revenue_per_harvested_acre": 52.425,
      "yield": 23.3
    },
    "1962": {
      "marketing_year": "1962",
      "price": 2.33,
      "revenue_per_harvested_acre": 40.076,
      "yield": 17.2
    },
    "1963": {
      "marketing_year": "1963",
      "price": 2.51,
      "revenue_per_harvested_acre": 57.228,
      "yield": 22.8
    },
    "1964": {
      "marketing_year": "1964",
      "price": 2.64,
      "revenue_per_harvested_acre": 60.192,
      "yield": 22.8
    },
    "1965": {
      "marketing_year": "1965",
      "price": 2.48,
      "revenue_per_harvested_acre": 62.496,
      "yield": 25.2
    },
    "1966": {
      "marketing_year": "1966",
      "price": 2.77,
      "revenue_per_harvested_acre": 67.034,
      "yield": 24.2
    },
    "1967": {
      "marketing_year": "1967",
      "price": 2.48,
      "revenue_per_harvested_acre": 72.912,
      "yield": 29.4
    },
    "1968": {
      "marketing_year": "1968",
      "price": 2.4,
      "revenue_per_harvested_acre": 73.68,
      "yield": 30.7
    },
    "1969": {
      "marketing_year": "1969",
      "price": 2.29,
      "revenue_per_harvested_acre": 68.929,
      "yield": 30.1
    },
    "1970": {
      "marketing_year": "1970",
      "price": 2.85,
      "revenue_per_harvested_acre": 74.385,
      "yield": 26.1
    },
    "1971": {
      "marketing_year": "1971",
      "price": 2.97,
      "revenue_per_harvested_acre": 87.021,
      "yield": 29.3
    },
    "1972": {
      "marketing_year": "1972",
      "price": 4.25,
      "revenue_per_harvested_acre": 108.8,
      "yield": 25.6
    },
    "1973": {
      "marketing_year": "1973",
      "price": 5.72,
      "revenue_per_harvested_acre": 139.568,
      "yield": 24.4
    },
    "1974": {
      "marketing_year": "1974",
      "price": 7.05,
      "revenue_per_harvested_acre": 174.135,
      "revenue_per_planted_acre": 167.908,
      "yield": 24.7
    },
    "1975": {
      "marketing_year": "1975",
      "price": 4.98,
      "revenue_per_harvested_acre": 142.926,
      "revenue_per_planted_acre": 142.3736,
      "yield": 28.7
    },
    "1976": {
      "marketing_year": "1976",
      "price": 6.7,
      "revenue_per_harvested_acre": 200.33,
      "revenue_per_planted_acre": 199.9912,
      "yield": 29.9
    },
    "1977": {
      "marketing_year": "1977",
      "price": 5.59,
      "revenue_per_harvested_acre": 180.557,
      "revenue_per_planted_acre": 179.4798,
      "yield": 32.3
    },
    "1978": {
      "marketing_year": "1978",
      "price": 6.68,
      "revenue_per_harvested_acre": 195.056,
      "revenue_per_planted_acre": 194.5857,
      "yield": 29.2
    },
    "1979": {
      "marketing_year": "1979",
      "price": 6.32,
      "revenue_per_harvested_acre": 195.92,
      "revenue_per_planted_acre": 191.6932,
      "yield": 31.0
    },
    "1980": {
      "marketing_year": "1980",
      "price": 7.6,
      "revenue_per_harvested_acre": 221.92,
      "revenue_per_planted_acre": 221.6253,
      "yield": 29.2
    },
    "1981": {
      "marketing_year": "1981",
      "price": 6.09,
      "revenue_per_harvested_acre": 200.361,
      "revenue_per_planted_acre": 199.0924,
      "yield": 32.9
    },
    "1982": {
      "marketing_year": "1982",
      "price": 5.51,
      "revenue_per_harvested_acre": 177.973,
      "revenue_per_planted_acre": 175.3546,
      "yield": 32.3
    },
    "1983": {
      "marketing_year": "1983",
      "price": 7.96,
      "revenue_per_harvested_acre": 151.24,
      "revenue_per_planted_acre": 149.3515,
      "yield": 19.0
    },
    "1984": {
      "marketing_year": "1984",
      "price": 5.9,
      "revenue_per_harvested_acre": 177.59,
      "revenue_per_planted_acre": 176.475,
      "yield": 30.1
    },
    "1985": {
      "marketing_year": "1985",
      "price": 5.04,
      "revenue_per_harvested_acre": 167.328,
      "revenue_per_planted_acre": 166.1422,
      "yield": 33.2
    },
    "1986": {
      "marketing_year": "1986",
      "price": 4.76,
      "revenue_per_harvested_acre": 166.124,
      "revenue_per_planted_acre": 163.8342,
      "yield": 34.9
    },
    "1987": {
      "marketing_year": "1987",
      "price": 5.94,
      "revenue_per_harvested_acre": 174.042,
      "revenue_per_planted_acre": 170.2938,
      "yield": 29.3
    },
    "1988": {
      "marketing_year": "1988",
      "price": 7.55,
      "revenue_per_harvested_acre": 203.095,
      "revenue_per_planted_acre": 198.0019,
      "yield": 26.9
    },
    "1989": {
      "marketing_year": "1989",
      "price": 5.79,
      "revenue_per_harvested_acre": 191.07,
      "revenue_per_planted_acre": 188.5659,
      "yield": 33.0
    },
    "1990": {
      "marketing_year": "1990",
      "price": 5.81,
      "revenue_per_harvested_acre": 195.797,
      "revenue_per_planted_acre": 194.0606,
      "yield": 33.7
    },
    "1991": {
      "marketing_year": "1991",
      "price": 5.68,
      "revenue_per_harvested_acre": 168.696,
      "revenue_per_planted_acre": 166.3953,
      "yield": 29.7
    },
    "1992": {
      "marketing_year": "1992",
      "price": 5.61,
      "revenue_per_harvested_acre": 222.156,
      "revenue_per_planted_acre": 221.0201,
      "yield": 39.6
    },
    "1993": {
      "marketing_year": "1993",
      "price": 6.31,
      "revenue_per_harvested_acre": 222.743,
      "revenue_per_planted_acre": 221.7514,
      "yield": 35.3
    },
    "1994": {
      "marketing_year": "1994",
      "price": 5.53,
      "revenue_per_harvested_acre": 216.776,
      "revenue_per_planted_acre": 215.8607,
      "yield": 39.2
    },
    "1995": {
      "marketing_year": "1995",
      "price": 6.73,
      "revenue_per_harvested_acre": 228.147,
      "revenue_per_planted_acre": 227.0318,
      "yield": 33.9
    },
    "1996": {
      "marketing_year": "1996",
      "price": 7.34,
      "revenue_per_harvested_acre": 264.974,
      "revenue_per_planted_acre": 264.5779,
      "yield": 36.1
    },
    "1997": {
      "marketing_year": "1997",
      "price": 6.59,
      "revenue_per_harvested_acre": 229.332,
      "revenue_per_planted_acre": 226.8108,
      "yield": 34.8
    },
    "1998": {
      "marketing_year": "1998",
      "price": 5.05,
      "revenue_per_harvested_acre": 148.47,
      "revenue_per_planted_acre": 147.9511,
      "yield": 29.4
    },
    "1999": {
      "marketing_year": "1999",
      "price": 4.71,
      "revenue_per_harvested_acre": 106.917,
      "revenue_per_planted_acre": 105.0488,
      "yield": 22.7
    },
    "2000": {
      "marketing_year": "2000",
      "price": 4.61,
      "revenue_per_harvested_acre": 202.84,
      "revenue_per_planted_acre": 202.4086,
      "yield": 44.0
    },
    "2001": {
      "marketing_year": "2001",
      "price": 4.42,
      "revenue_per_harvested_acre": 190.502,
      "revenue_per_planted_acre": 190.3694,
      "yield": 43.1
    },
    "2002": {
      "marketing_year": "2002",
      "price": 5.55,
      "revenue_per_harvested_acre": 162.615,
      "revenue_per_planted_acre": 161.007,
      "yield": 29.3
    },
    "2003": {
      "marketing_year": "2003",
      "price": 7.67,
      "revenue_per_harvested_acre": 336.713,
      "revenue_per_planted_acre": 336.2445,
      "yield": 43.9
    },
    "2004": {
      "marketing_year": "2004",
      "price": 5.66,
      "revenue_per_harvested_acre": 229.23,
      "revenue_per_planted_acre": 227.3759,
      "yield": 40.5
    },
    "2005": {
      "marketing_year": "2005",
      "price": 5.78,
      "revenue_per_harvested_acre": 275.128,
      "revenue_per_planted_acre": 274.0514,
      "yield": 47.6
    },
    "2006": {
      "marketing_year": "2006",
      "price": 6.53,
      "revenue_per_harvested_acre": 289.279,
      "revenue_per_planted_acre": 286.9619,
      "yield": 44.3
    },
    "2007": {
      "marketing_year": "2007",
      "price": 10.2,
      "revenue_per_harvested_acre": 401.88,
      "revenue_per_planted_acre": 400.6066,
      "yield": 39.4
    },
    "2008": {
      "marketing_year": "2008",
      "price": 10.2,
      "revenue_per_harvested_acre": 382.5,
      "revenue_per_planted_acre": 381.4108,
      "yield": 37.5
    },
    "2009": {
      "marketing_year": "2009",
      "price": 9.8,
      "revenue_per_harvested_acre": 480.2,
      "revenue_per_planted_acre": 481.0671,
      "yield": 49.0
    },
    "2010": {
      "marketing_year": "2010",
      "price": 11.5,
      "revenue_per_harvested_acre": 480.7,
      "revenue_per_planted_acre": 480.594,
      "yield": 41.8
    },
    "2011": {
      "marketing_year": "2011",
      "price": 12.7,
      "revenue_per_harvested_acre": 478.79,
      "revenue_per_planted_acre": 478.9714,
      "yield": 37.7
    },
    "2012": {
      "marketing_year": "2012",
      "price": 14.7,
      "revenue_per_harvested_acre": 633.57,
      "revenue_per_planted_acre": 632.2374,
      "yield": 43.1
    },
    "2013": {
      "marketing_year": "2013",
      "price": 13.2,
      "revenue_per_harvested_acre": 682.44,
      "revenue_per_planted_acre": 682.1106,
      "yield": 51.7
    },
    "2014": {
      "marketing_year": "2014",
      "price": 10.2,
      "revenue_per_harvested_acre": 519.18,
      "revenue_per_planted_acre": 519.6667,
      "yield": 50.9
    },
    "2015": {
      "marketing_year": "2015",
      "price": 9.16,
      "revenue_per_harvested_acre": 487.312,
      "revenue_per_planted_acre": 486.3557,
      "yield": 53.2
    },
    "2016": {
      "marketing_year": "2016",
      "price": 9.69,
      "revenue_per_harvested_acre": 507.756,
      "revenue_per_planted_acre": 507.0315,
      "yield": 52.4
    },
    "2017": {
      "marketing_year": "2017",
      "price": 9.61,
      "revenue_per_harvested_acre": 566.99,
      "revenue_per_planted_acre": 566.566,
      "yield": 59.0
    },
    "2018": {
      "marketing_year": "2018",
      "price": 8.73,
      "revenue_per_harvested_acre": 446.103,
      "revenue_per_planted_acre": 443.8178,
      "yield": 51.1
    },
    "2019": {
      "marketing_year": "2019",
      "price": 8.92,
      "revenue_per_harvested_acre": 475.436,
      "revenue_per_planted_acre": 470.4892,
      "yield": 53.3
    },
    "2020": {
      "marketing_year": "2020",
      "price": 11.1,
      "revenue_per_harvested_acre": 649.35,
      "revenue_per_planted_acre": 647.4727,
      "yield": 58.5
    },
    "2021": {
      "marketing_year": "2021",
      "price": 13.3,
      "revenue_per_harvested_acre": 798.0,
      "revenue_per_planted_acre": 796.7854,
      "yield": 60.0
    },
    "2024": {
      "marketing_year": "2024",
      "price": 10.4,
      "revenue_per_harvested_acre": 563.68,
      "revenue_per_planted_acre": 560.6339,
      "yield": 54.2
    },
    "2025": {
      "marketing_year": "2025",
      "price": 10.4,
      "revenue_per_harvested_acre": 562.64,
      "revenue_per_planted_acre": 560.8284,
      "yield": 54.1
    }
  },
  "schema_version": 3,
  "state": {
    "alpha": "IN",
    "fips": "18",
    "name": "INDIANA"
  },
  "yield_trend": {
    "slope_bu_per_year": 0.4827,
    "trailing_10yr_avg": {
      "1941": 14.3,
      "1942": 14.2,
      "1943": 13.71,
      "1944": 13.79,
      "1945": 14.08,
      "1946": 14.21,
      "1947": 14.17,
      "1948": 14.06,
      "1949": 14.18,
      "1950": 14.68,
      "1951": 14.89,
      "1952": 14.85,
      "1953": 14.96,
      "1954": 15.0,
      "1955": 14.83,
      "1956": 15.77,
      "1957": 16.16,
      "1958": 16.82,
      "1959": 17.71,
      "1960": 17.77,
      "1961": 18.39,
      "1962": 18.78,
      "1963": 19.87,
      "1964": 20.68,
      "1965": 21.73,
      "1966": 21.67,
      "1967": 22.86,
      "1968": 23.65,
      "1969": 24.27,
      "1970": 25.18,
      "1971": 25.78,
      "1972": 26.62,
      "1973": 26.78,
      "1974": 26.97,
      "1975": 27.32,
      "1976": 27.89,
      "1977": 28.18,
      "1978": 28.03,
      "1979": 28.12,
      "1980": 28.43,
      "1981": 28.79,
      "1982": 29.46,
      "1983": 28.92,
      "1984": 29.46,
      "1985": 29.91,
      "1986": 30.41,
      "1987": 30.11,
      "1988": 29.88,
      "1989": 30.08,
      "1990": 30.53,
      "1991": 30.21,
      "1992": 30.94,
      "1993": 32.57,
      "1994": 33.48,
      "1995": 33.55,
      "1996": 33.67,
      "1997": 34.22,
      "1998": 34.47,
      "1999": 33.44,
      "2000": 34.47,
      "2001": 35.81,
      "2002": 34.78,
      "2003": 35.64,
      "2004": 35.77,
      "2005": 37.14,
      "2006": 37.96,
      "2007": 38.42,
      "2008": 39.23,
      "2009": 41.86,
      "2010": 41.64,
      "2011": 41.1,
      "2012": 42.48,
      "2013": 43.26,
      "2014": 44.3,
      "2015": 44.86,
      "2016": 45.67,
      "2017": 47.63,
      "2018": 48.99,
      "2019": 49.42,
      "2020": 51.09,
      "2021": 53.32,
      "2024": 55.21,
      "2025": 55.33
    },
    "trailing_5yr_avg": {
      "1939": 15.03,
      "1940": 14.12,
      "1941": 14.3,
      "1942": 14.24,
      "1943": 12.94,
      "1944": 13.04,
      "1945": 14.04,
      "1946": 14.12,
      "1947": 14.1,
      "1948": 15.18,
      "1949": 15.32,
      "1950": 15.32,
      "1951": 15.66,
      "1952": 15.6,
      "1953": 14.74,
      "1954": 14.68,
      "1955": 14.34,
      "1956": 15.88,
      "1957": 16.72,
      "1958": 18.9,
      "1959": 20.74,
      "1960": 21.2,
      "1961": 20.9,
      "1962": 20.84,
      "1963": 20.84,
      "1964": 20.62,
      "1965": 22.26,
      "1966": 22.44,
      "1967": 24.88,
      "1968": 26.46,
      "1969": 27.92,
      "1970": 28.1,
      "1971": 29.12,
      "1972": 28.36,
      "1973": 27.1,
      "1974": 26.02,
      "1975": 26.54,
      "1976": 26.66,
      "1977": 28.0,
      "1978": 28.96,
      "1979": 30.22,
      "1980": 30.32,
      "1981": 30.92,
      "1982": 30.92,
      "1983": 28.88,
      "1984": 28.7,
      "1985": 29.5,
      "1986": 29.9,
      "1987": 29.3,
      "1988": 30.88,
      "1989": 31.46,
      "1990": 31.56,
      "1991": 30.52,
      "1992": 32.58,
      "1993": 34.26,
      "1994": 35.5,
      "1995": 35.54,
      "1996": 36.82,
      "1997": 35.86,
      "1998": 34.68,
      "1999": 31.38,
      "2000": 33.4,
      "2001": 34.8,
      "2002": 33.7,
      "2003": 36.6,
      "2004": 40.16,
      "2005": 40.88,
      "2006": 41.12,
      "2007": 43.14,
      "2008": 41.86,
      "2009": 43.56,
      "2010": 42.4,
      "2011": 41.08,
      "2012": 41.82,
      "2013": 44.66,
      "2014": 45.04,
      "2015": 47.32,
      "2016": 50.26,
      "2017": 53.44,
      "2018": 53.32,
      "2019": 53.8,
      "2020": 54.86,
      "2021": 56.38,
      "2024": 57.57,
      "2025": 56.1
    },
    "yoy_pct": {
      "1938": 23.57,
      "1939": -20.23,
      "1940": -17.39,
      "1941": 31.58,
      "1942": -8.67,
      "1943": -21.17,
      "1944": 32.41,
      "1945": 14.69,
      "1946": -6.1,
      "1947": -11.69,
      "1948": 19.12,
      "1949": -7.41,
      "1950": 9.33,
      "1951": 4.27,
      "1952": -22.22,
      "1953": -10.53,
      "1954": 23.53,
      "1955": 0.0,
      "1956": 68.71,
      "1957": -29.44,
      "1958": 30.29,
      "1959": 4.82,
      "1960": -28.87,
      "1961": 37.06,
      "1962": -26.18,
      "1963": 32.56,
      "1964": 0.0,
      "1965": 10.53,
      "1966": -3.97,
      "1967": 21.49,
      "1968": 4.42,
      "1969": -1.95,
      "1970": -13.29,
      "1971": 12.26,
      "1972": -12.63,
      "1973": -4.69,
      "1974": 1.23,
      "1975": 16.19,
      "1976": 4.18,
      "1977": 8.03,
      "1978": -9.6,
      "1979": 6.16,
      "1980": -5.81,
      "1981": 12.67,
      "1982": -1.82,
      "1983": -41.18,
      "1984": 58.42,
      "1985": 10.3,
      "1986": 5.12,
      "1987": -16.05,
      "1988": -8.19,
      "1989": 22.68,
      "1990": 2.12,
      "1991": -11.87,
      "1992": 33.33,
      "1993": -10.86,
      "1994": 11.05,
      "1995": -13.52,
      "1996": 6.49,
      "1997": -3.6,
      "1998": -15.52,
      "1999": -22.79,
      "2000": 93.83,
      "2001": -2.05,
      "2002": -32.02,
      "2003": 49.83,
      "2004": -7.74,
      "2005": 17.53,
      "2006": -6.93,
      "2007": -11.06,
      "2008": -4.82,
      "2009": 30.67,
      "2010": -14.69,
      "2011": -9.81,
      "2012": 14.32,
      "2013": 19.95,
      "2014": -1.55,
      "2015": 4.52,
      "2016": -1.5,
      "2017": 12.6,
      "2018": -13.39,
      "2019": 4.31,
      "2020": 9.76,
      "2021": 2.56,
      "2025": -0.18
    }
  }
}
