{
  "commodity": {
    "desc": "SOYBEANS",
    "slug": "soybeans"
  },
  "county": {
    "code": "117",
    "name": "KENTON"
  },
  "schema_version": 3,
  "series": [
    {
      "canonical": true,
      "class": "ALL CLASSES",
      "cv": {
        "2021": 3.9,
        "2023": 1.0
      },
      "prodn_practice": "ALL PRODUCTION PRACTICES",
      "raw": {},
      "short_desc": "SOYBEANS - ACRES HARVESTED",
      "statistic": "AREA HARVESTED",
      "suppressed": {},
      "unit": "ACRES",
      "util_practice": "ALL UTILIZATION PRACTICES",
      "values": {
        "1972": 100.0,
        "1975": 200.0,
        "1976": 200.0,
        "2021": 400.0,
        "2023": 300.0
      }
    },
    {
      "canonical": true,
      "class": "ALL CLASSES",
      "cv": {
        "2021": 3.9,
        "2023": 0.7
      },
      "prodn_practice": "ALL PRODUCTION PRACTICES",
      "raw": {},
      "short_desc": "SOYBEANS - ACRES PLANTED",
      "statistic": "AREA PLANTED",
      "suppressed": {},
      "unit": "ACRES",
      "util_practice": "ALL UTILIZATION PRACTICES",
      "values": {
        "1975": 300.0,
        "1976": 300.0,
        "2021": 400.0,
        "2023": 300.0
      }
    },
    {
      "canonical": true,
      "class": "ALL CLASSES",
      "cv": {
        "2021": 4.1,
        "2023": 5.5
      },
      "prodn_practice": "ALL PRODUCTION PRACTICES",
      "raw": {},
      "short_desc": "SOYBEANS - PRODUCTION, MEASURED IN BU",
      "statistic": "PRODUCTION",
      "suppressed": {},
      "unit": "BU",
      "util_practice": "ALL UTILIZATION PRACTICES",
      "values": {
        "1972": 2500.0,
        "1975": 6200.0,
        "1976": 6300.0,
        "2021": 20500.0,
        "2023": 15900.0
      }
    },
    {
      "canonical": true,
      "class": "ALL CLASSES",
      "cv": {
        "2021": 1.4,
        "2023": 5.5
      },
      "prodn_practice": "ALL PRODUCTION PRACTICES",
      "raw": {},
      "short_desc": "SOYBEANS - YIELD, MEASURED IN BU / ACRE",
      "statistic": "YIELD",
      "suppressed": {},
      "unit": "BU / ACRE",
      "util_practice": "ALL UTILIZATION PRACTICES",
      "values": {
        "1972": 25.0,
        "1975": 31.0,
        "1976": 31.5,
        "2021": 51.3,
        "2023": 53.0
      }
    }
  ],
  "state": {
    "alpha": "KY",
    "fips": "21",
    "name": "KENTUCKY"
  }
}
