{
  "commodity": {
    "desc": "CORN",
    "slug": "corn"
  },
  "county": {
    "code": "067",
    "name": "MOREHOUSE"
  },
  "schema_version": 2,
  "series": [
    {
      "canonical": true,
      "class": "ALL CLASSES",
      "prodn_practice": "ALL PRODUCTION PRACTICES",
      "raw": {},
      "short_desc": "CORN, GRAIN - YIELD, MEASURED IN BU / ACRE",
      "suppressed": {},
      "unit": "BU / ACRE",
      "util_practice": "GRAIN",
      "values": {
        "1959": 36.0,
        "1960": 32.8,
        "1961": 53.0,
        "1962": 25.0,
        "1963": 29.5,
        "1964": 25.0,
        "1965": 34.1,
        "1966": 25.0,
        "1967": 50.0,
        "1968": 35.0,
        "1969": 30.0,
        "1970": 55.0,
        "1971": 40.0,
        "1972": 40.0,
        "1973": 35.0,
        "1974": 33.0,
        "1975": 40.0,
        "1976": 45.0,
        "1977": 65.0,
        "1978": 60.0,
        "1979": 56.0,
        "1980": 25.0,
        "1982": 55.0,
        "1983": 60.0,
        "1984": 92.0,
        "1985": 55.0,
        "1986": 90.0,
        "1987": 137.5,
        "1988": 110.0,
        "1989": 105.0,
        "1990": 112.5,
        "1991": 93.3,
        "1992": 156.3,
        "1993": 100.0,
        "1994": 139.1,
        "1995": 125.0,
        "1996": 123.0,
        "1997": 138.5,
        "1998": 108.0,
        "1999": 151.2,
        "2000": 133.1,
        "2001": 157.9,
        "2002": 126.1,
        "2003": 139.9,
        "2004": 140.2,
        "2005": 157.8,
        "2006": 158.0,
        "2007": 179.0,
        "2008": 156.0,
        "2009": 158.0,
        "2010": 162.1,
        "2011": 162.0,
        "2012": 181.1,
        "2013": 173.1,
        "2014": 192.1,
        "2015": 188.0,
        "2016": 175.5,
        "2017": 193.8,
        "2018": 169.0,
        "2019": 173.0,
        "2020": 174.8,
        "2021": 196.6,
        "2022": 188.7,
        "2023": 185.3,
        "2024": 192.0
      }
    },
    {
      "class": "ALL CLASSES",
      "prodn_practice": "ALL PRODUCTION PRACTICES",
      "raw": {},
      "short_desc": "CORN, GRAIN - YIELD, MEASURED IN BU / NET PLANTED ACRE",
      "suppressed": {},
      "unit": "BU / NET PLANTED ACRE",
      "util_practice": "GRAIN",
      "values": {
        "1978": 51.4,
        "1979": 56.0,
        "1980": 20.0,
        "1982": 55.0,
        "1983": 60.0,
        "1984": 92.0,
        "1985": 34.4
      }
    }
  ],
  "state": {
    "alpha": "LA",
    "fips": "22",
    "name": "LOUISIANA"
  }
}
